kmerator/__init__.py
kmerator/color.py
kmerator/config.py
kmerator/dataset.py
kmerator/exit.py
kmerator/geneinfo.py
kmerator/info.py
kmerator/kmerator.py
kmerator/kmerize.py
kmerator/longest_transcript.py
kmerator/mk_geneinfo.py
kmerator/mk_transcriptome.py
kmerator/options.py
kmerator-2.3.4.dist-info/licenses/LICENCE.md
kmerator-2.3.4.dist-info/METADATA
kmerator-2.3.4.dist-info/WHEEL
kmerator-2.3.4.dist-info/entry_points.txt
kmerator-2.3.4.dist-info/top_level.txt
kmerator-2.3.4.dist-info/RECORD
