Metadata-Version: 2.4
Name: kmerator
Version: 2.3.4
Summary: Find specific gene or transcript kmers. And more.
Home-page: https://github.com/Transipedia/kmerator
Author: Sébastien RIQUIER, IRMB, Montpellier
Author-email: sebastien.riquier@ucd.ie
License: GPLv3
Classifier: Development Status :: 4 - Beta
Classifier: Environment :: Console
Classifier: Intended Audience :: Science/Research
Classifier: License :: OSI Approved :: GNU General Public License v3 (GPLv3)
Classifier: Operating System :: POSIX :: Linux
Classifier: Programming Language :: Python :: 3
Classifier: Natural Language :: English
Classifier: Topic :: Scientific/Engineering :: Bio-Informatics
Requires-Python: >=3.7
License-File: LICENCE.md
Requires-Dist: bs4
Requires-Dist: lxml
Requires-Dist: requests
Dynamic: author
Dynamic: author-email
Dynamic: classifier
Dynamic: description
Dynamic: description-content-type
Dynamic: home-page
Dynamic: license
Dynamic: license-file
Dynamic: requires-dist
Dynamic: requires-python
Dynamic: summary
